minecraft_data_py/__init__.py
minecraft_data_py/data.py
minecraft_data_py-1.0.0.dist-info/LICENSE
minecraft_data_py-1.0.0.dist-info/METADATA
minecraft_data_py-1.0.0.dist-info/WHEEL
minecraft_data_py-1.0.0.dist-info/top_level.txt
minecraft_data_py-1.0.0.dist-info/RECORD
